cursor_rules/__init__.py
cursor_rules/cli.py
cursor_rules/code_monitor.py
cursor_rules/core.py
cursor_rules/document_generator.py
cursor_rules/dynamic_rules.py
cursor_rules/executor.py
cursor_rules/llm_connector.py
cursor_rules/llm_enhancer.py
cursor_rules/parser.py
cursor_rules/phase_manager.py
cursor_rules/task_parser.py
cursor_rules/task_tracker.py
cursor_rules/terminal_utils.py
cursor_rules/test_action_items.py
cursor_rules/utils.py
cursor_rules/versioning.py
dynamic_cursor_rules-1.10.5.data/scripts/cursor-rules
dynamic_cursor_rules-1.10.5.data/scripts/cursor-tasks
dynamic_cursor_rules-1.10.5.dist-info/licenses/LICENSE
tests/__init__.py
tests/test_core.py
tests/test_cursorrules_generation.py
dynamic_cursor_rules-1.10.5.dist-info/METADATA
dynamic_cursor_rules-1.10.5.dist-info/WHEEL
dynamic_cursor_rules-1.10.5.dist-info/entry_points.txt
dynamic_cursor_rules-1.10.5.dist-info/top_level.txt
dynamic_cursor_rules-1.10.5.dist-info/RECORD
