Metadata-Version: 2.4
Name: dynamic-cursor-rules
Version: 1.10.5
Summary: Generate and manage documentation and task tracking for Cursor IDE projects
Home-page: https://github.com/cursor-rules/cursor-rules
Author: Cursor Rules Team
Author-email: info@cursorrules.dev
Project-URL: Bug Tracker, https://github.com/cursor-rules/cursor-rules/issues
Project-URL: Documentation, https://github.com/cursor-rules/cursor-rules#readme
Project-URL: Source Code, https://github.com/cursor-rules/cursor-rules
Keywords: cursor,ide,documentation,rules,ai,tasks,project-management
Classifier: Development Status :: 5 - Production/Stable
Classifier: Intended Audience :: Developers
Classifier: Topic :: Software Development :: Documentation
Classifier: Topic :: Software Development :: Libraries :: Python Modules
Classifier: Programming Language :: Python :: 3
Classifier: Programming Language :: Python :: 3.9
Classifier: Programming Language :: Python :: 3.10
Classifier: Programming Language :: Python :: 3.11
Classifier: License :: OSI Approved :: MIT License
Classifier: Operating System :: OS Independent
Requires-Python: >=3.9
License-File: LICENSE
Requires-Dist: pyyaml>=6.0
Requires-Dist: markdown>=3.3.0
Requires-Dist: gitpython>=3.1.0
Requires-Dist: openai>=1.0.0
Requires-Dist: anthropic>=0.5.0
Requires-Dist: colorama>=0.4.4
Requires-Dist: tqdm>=4.65.0
Requires-Dist: yaspin>=2.3.0
Provides-Extra: dev
Requires-Dist: pytest>=7.0.0; extra == "dev"
Requires-Dist: pytest-cov>=3.0.0; extra == "dev"
Requires-Dist: black>=22.0.0; extra == "dev"
Requires-Dist: isort>=5.0.0; extra == "dev"
Requires-Dist: flake8>=4.0.0; extra == "dev"
Requires-Dist: build>=0.10.0; extra == "dev"
Requires-Dist: twine>=4.0.0; extra == "dev"
Dynamic: author
Dynamic: author-email
Dynamic: classifier
Dynamic: description
Dynamic: description-content-type
Dynamic: home-page
Dynamic: keywords
Dynamic: license-file
Dynamic: project-url
Dynamic: provides-extra
Dynamic: requires-dist
Dynamic: requires-python
Dynamic: summary
